{
    "version": 8,
    "configurePresets": [
        {
            "name": "VCPKG",
            "displayName": "VCPKG",
            "description": "Uses VCPKG package manager for finding dependencies",
            "generator": "Visual Studio 17 2022",
            "binaryDir": "${sourceDir}/out/build/${presetName}",
            "cacheVariables": {
                "CMAKE_BUILD_TYPE": "Debug",
                "CMAKE_TOOLCHAIN_FILE": "${env:VCPKG_ROOT}/scripts/buildsystems/vcpkg.cmake",
                "CMAKE_INSTALL_PREFIX": "${sourceDir}/out/install/${presetName}"
            }
        },
        {
            "name": "msvc-x64",
            "displayName": "Visual Studio Community 2022 Release - amd64",
            "description": "Using compilers for Visual Studio 17 2022 (x64 architecture)",
            "generator": "Visual Studio 17 2022",
            "toolset": "host=x64",
            "architecture": "x64",
            "binaryDir": "${sourceDir}/out/build/${presetName}",
            "cacheVariables": {
                "CMAKE_INSTALL_PREFIX": "${sourceDir}/out/install/${presetName}",
                "CMAKE_C_COMPILER": "cl.exe",
                "CMAKE_CXX_COMPILER": "cl.exe"
            }
        },
        {
            "name": "CLang-x86_64-linux",
            "displayName": "Clang 19.1.1 x86_64-pc-linux-gnu",
            "description": "Using compilers: C = /usr/bin/clang-19, CXX = /usr/bin/clang++-19",
            "binaryDir": "${sourceDir}/out/build/${presetName}",
            "cacheVariables": {
                "CMAKE_INSTALL_PREFIX": "${sourceDir}/out/install/${presetName}",
                "CMAKE_C_COMPILER": "/usr/bin/clang-19",
                "CMAKE_CXX_COMPILER": "/usr/bin/clang++-19",
                "CMAKE_BUILD_TYPE": "Debug"
            }
        },
        {
            "name": "Clang-x64",
            "description": "",
            "displayName": "",
            "cacheVariables": {
                "CMAKE_C_COMPILER": "d:/soft/clang-18/bin/clang.exe",
                "CMAKE_CXX_COMPILER": "d:/soft/clang-18/bin/clang++.exe"
            },
            "inherits": [
                "CLang-x86_64-linux"
            ]
        }
    ],
    "buildPresets": [
        {
            "name": "msvc-x64-debug",
            "displayName": "Visual Studio Community 2022 Release - amd64 - Debug",
            "configurePreset": "msvc-x64",
            "configuration": "Debug"
        },
        {
            "name": "VS 2022 Release",
            "description": "",
            "displayName": "",
            "configuration": "Release",
            "inherits": [
                "msvc-x64-debug"
            ]
        }
    ]
}